pdbparser/Globals.py
pdbparser/__init__.py
pdbparser/__pkginfo__.py
pdbparser/log.py
pdbparser/pdbparser.py
pdbparser/setup.py
pdbparser/Analysis/Core.py
pdbparser/Analysis/__init__.py
pdbparser/Analysis/Dynamics/HydrogenBonds.py
pdbparser/Analysis/Dynamics/MeanSquareDisplacement.py
pdbparser/Analysis/Dynamics/__init__.py
pdbparser/Analysis/Structure/CylindricalDensity.py
pdbparser/Analysis/Structure/Distances.py
pdbparser/Analysis/Structure/Eccentricity.py
pdbparser/Analysis/Structure/SolventAccessibleSurfaceArea.py
pdbparser/Analysis/Structure/__init__.py
pdbparser/Analysis/Trajectory/BuildAtomsCluster.py
pdbparser/Analysis/Trajectory/CenterOfMassTranslated.py
pdbparser/Analysis/Trajectory/GlobalMotionFiltered.py
pdbparser/Analysis/Trajectory/__init__.py
pdbparser/Data/__init__.py
pdbparser/Examples/__init__.py
pdbparser/Examples/amorphousSystem.py
pdbparser/Examples/analysisSASA.py
pdbparser/Examples/argonSimulation.py
pdbparser/Examples/carbonNanotube.py
pdbparser/Examples/connectivity.py
pdbparser/Examples/liposome.py
pdbparser/Examples/micelle.py
pdbparser/Examples/nanotubeSelection.py
pdbparser/Examples/records.py
pdbparser/Examples/simulationBondAngleInteraction.py
pdbparser/Examples/simulationDihedral.py
pdbparser/Examples/simulationNonBonded.py
pdbparser/Examples/waterSphere.py
pdbparser/IO/Core.py
pdbparser/IO/TrajectoryConverter.py
pdbparser/IO/__init__.py
pdbparser/UnitTests/RunTests.py
pdbparser/UnitTests/TestConnectivity.py
pdbparser/UnitTests/TestTranslation.py
pdbparser/UnitTests/__init__.py
pdbparser/Utilities/BoundaryConditions.py
pdbparser/Utilities/Collection.py
pdbparser/Utilities/Connectivity.py
pdbparser/Utilities/Construct.py
pdbparser/Utilities/Convert.py
pdbparser/Utilities/Database.py
pdbparser/Utilities/Geometry.py
pdbparser/Utilities/Information.py
pdbparser/Utilities/Math.py
pdbparser/Utilities/Modify.py
pdbparser/Utilities/Selection.py
pdbparser/Utilities/Simulate.py
pdbparser/Utilities/Symmetry.py
pdbparser/Utilities/__init__.py
pdbparser-0.1.8.dist-info/METADATA
pdbparser-0.1.8.dist-info/WHEEL
pdbparser-0.1.8.dist-info/top_level.txt
pdbparser-0.1.8.dist-info/RECORD
