Metadata-Version: 2.1
Name: pdbparser
Version: 0.1.8
Summary: It's a Protein Data Bank (.pdb) files manipulation package that is mainly developed to parse and load, duplicate, manipulate and create pdb files.
Home-page: UNKNOWN
Author: Bachir AOUN
Author-email: bachir.aoun@e-aoun.com
License: GNU
Platform: Windows
Platform: Linux
Platform: Solaris
Platform: Mac OS-X
Platform: Unix
Classifier: Development Status :: 4 - Beta
Classifier: Intended Audience :: Science/Research
Classifier: Intended Audience :: Developers
Classifier: License :: OSI Approved :: GNU Affero General Public License v3
Classifier: Programming Language :: Python :: 2.7
Classifier: Programming Language :: Python :: 3
Classifier: Topic :: Software Development
Classifier: Topic :: Software Development :: Build Tools
Classifier: Topic :: Scientific/Engineering
Classifier: Operating System :: Microsoft :: Windows
Classifier: Operating System :: POSIX
Classifier: Operating System :: Unix
Classifier: Operating System :: MacOS
Requires-Dist: pysimplelog
Requires-Dist: pypref
